{
  "sorted_middleware": [],
  "middleware": {
    "/": {
      "files": [
        "server/edge/chunks/_938286ba._.js",
        "server/edge/chunks/[root-of-the-server]__15d07629._.js",
        "server/edge/chunks/edge-wrapper_3be04e37.js"
      ],
      "name": "middleware",
      "page": "/",
      "matchers": [
        {
          "regexp": "/:nextData(_next/data/[^/]{1,})?/((?!api|_next/static|_next/image|favicon.ico|.*\\.[^/]+$).*){(\\\\.json)}?",
          "originalSource": "/((?!api|_next/static|_next/image|favicon.ico|.*\\.[^/]+$).*)"
        }
      ],
      "wasm": [],
      "assets": [],
      "env": {
        "__NEXT_BUILD_ID": "development",
        "NEXT_SERVER_ACTIONS_ENCRYPTION_KEY": "oD/K8KFMPz9QxCcWju/dDSl0qTw9rYrQv+Nz0neRjmY=",
        "__NEXT_PREVIEW_MODE_ID": "87c2f5d7b2808ced7d4dfc1e48ced64f",
        "__NEXT_PREVIEW_MODE_ENCRYPTION_KEY": "be3dc40c6c209a1540ce575024b7380206cea6c7860cfffd544cce9d001404fd",
        "__NEXT_PREVIEW_MODE_SIGNING_KEY": "a25c81e46eec4cce3438ffe84b876bb6d02ca58150c66a1fca050177fdb56115"
      }
    }
  },
  "instrumentation": null,
  "functions": {}
}